health_monitoring_plugins/__init__.py
health_monitoring_plugins/cambium.py
health_monitoring_plugins/eaton.py
health_monitoring_plugins/eps_plus.py
health_monitoring_plugins/idrac.py
health_monitoring_plugins/ilo.py
health_monitoring_plugins/inradios_csm.py
health_monitoring_plugins/ipport.py
health_monitoring_plugins/meinberg.py
health_monitoring_plugins/microwavemodem.py
health_monitoring_plugins/newtecmodem.py
health_monitoring_plugins/plugin_rules.md
health_monitoring_plugins/procurve.py
health_monitoring_plugins/raritan.py
health_monitoring_plugins/snmpSessionBaseClass.py
health_monitoring_plugins/storage.py
health_monitoring_plugins/timesource.py
health_monitoring_plugins/trustedfilter.py
health_monitoring_plugins/windowsservice.py
health_monitoring_plugins/check_jenkins_api/check_jenkins_api.py
health_monitoring_plugins/check_local_cpu_temperature/check_local_cpu_temperature.py
health_monitoring_plugins/check_meinberg_ntp/check_meinberg_ntp.py
health_monitoring_plugins/check_microwavemodem/check_microwavemodem.py
health_monitoring_plugins/check_moxa_6000/check_moxa_6000.py
health_monitoring_plugins/check_newtecmodem/check_newtecmodem.py
health_monitoring_plugins/check_snmp_apc_ups/check_snmp_apc_ups.py
health_monitoring_plugins/check_snmp_cambium_ptp700/check_snmp_cambium_ptp700.py
health_monitoring_plugins/check_snmp_eaton_ups/check_snmp_eaton_ups.py
health_monitoring_plugins/check_snmp_eps_plus/check_snmp_eps_plus.py
health_monitoring_plugins/check_snmp_fortinet/check_snmp_fortinet.py
health_monitoring_plugins/check_snmp_idrac/check_snmp_idrac.py
health_monitoring_plugins/check_snmp_ilo4/check_snmp_ilo4.py
health_monitoring_plugins/check_snmp_inradios_csm/check_snmp_inradios_csm.py
health_monitoring_plugins/check_snmp_janitza/check_snmp_janitza.py
health_monitoring_plugins/check_snmp_large_storage/check_snmp_large_storage.py
health_monitoring_plugins/check_snmp_lband/check_snmp_lband.py
health_monitoring_plugins/check_snmp_port/check_snmp_port.py
health_monitoring_plugins-0.2.1.dist-info/LICENSE
health_monitoring_plugins-0.2.1.dist-info/METADATA
health_monitoring_plugins-0.2.1.dist-info/WHEEL
health_monitoring_plugins-0.2.1.dist-info/top_level.txt
health_monitoring_plugins-0.2.1.dist-info/RECORD
