Metadata-Version: 2.1
Name: health-monitoring-plugins
Version: 0.2.1
Summary: Health monitoring plugins for icinga/nagios
Home-page: https://codeberg.org/status_monitoring_tools/health_monitoring_plugins
Author: rsmuc
Author-email: rsmuc@sec-dev.de
License: GPLv2
Platform: UNKNOWN
Classifier: Topic :: System :: Monitoring
Classifier: Development Status :: 5 - Production/Stable
Requires-Dist: pynag
